Metadata-Version: 1.1
Name: db-integration-test
Version: 1.1.0
Summary: Easily setup relational database fixtures and assert database contents in unittest.
Home-page: https://github.com/flowpl/dbit
Author: Florian Plattner
Author-email: me@florianplattner.de
License: MIT
Keywords: testing
Platform: UNKNOWN
Classifier: Development Status :: 5 - Production/Stable
Classifier: Environment :: Other Environment
Classifier: Intended Audience :: Developers
Classifier: Intended Audience :: Information Technology
Classifier: License :: OSI Approved :: MIT License
Classifier: Operating System :: OS Independent
Classifier: Programming Language :: Python :: 3.5
Classifier: Programming Language :: Python :: 3.6
Classifier: Topic :: Software Development :: Libraries :: Python Modules
